pydiator_core/__init__.py
pydiator_core/default_pipeline.py
pydiator_core/interfaces.py
pydiator_core/logger.py
pydiator_core/mediatr.py
pydiator_core/mediatr_container.py
pydiator_core/serializer.py
pydiator_core/pipelines/__init__.py
pydiator_core/pipelines/cache_pipeline.py
pydiator_core/pipelines/log_pipeline.py
tests/__init__.py
tests/base_test_case.py
tests/test_default_pipeline.py
tests/test_mediator_container.py
tests/test_mediatr.py
tests/test_serializer.py
tests/test_serializer_factory.py
pydiator_core-1.0.12.dist-info/LICENSE
pydiator_core-1.0.12.dist-info/METADATA
pydiator_core-1.0.12.dist-info/WHEEL
pydiator_core-1.0.12.dist-info/top_level.txt
pydiator_core-1.0.12.dist-info/RECORD
