Metadata-Version: 2.1
Name: pydiator-core
Version: 1.0.12
Summary: Pydiator
Home-page: https://github.com/ozgurkara/pydiator-core
Author: Özgür Kara
Author-email: ozgurkara85@gmail.com
Classifier: Programming Language :: Python :: 3
Classifier: License :: OSI Approved :: MIT License
Classifier: Operating System :: OS Independent
License-File: LICENSE
